line_tools-0.0.4.dist-info/RECORD
line_tools-0.0.4.dist-info/metadata.json
line_tools-0.0.4.dist-info/WHEEL
line_tools-0.0.4.dist-info/entry_points.txt
line_tools-0.0.4.dist-info/DESCRIPTION.rst
line_tools-0.0.4.dist-info/top_level.txt
line_tools-0.0.4.dist-info/METADATA
linetools/__init__.py
linetools/line_richmenu.py
linetools/build_richmenu.py
