Metadata-Version: 2.0
Name: line-tools
Version: 0.0.4
Summary: A small set of utility useful when creating line BOT
Home-page: https://github.com/sohoffice/line-tools
Author: Douglas Liu
Author-email: douglas@sohoffice.com
License: UNKNOWN
Platform: UNKNOWN
Classifier: Programming Language :: Python :: 3
Classifier: License :: OSI Approved :: MIT License
Classifier: Operating System :: OS Independent
Requires-Dist: urllib3 (==1.23)
Requires-Dist: certifi (==2018.4.16)
